gq_py/__init__.py
gq_py/test.py
ganquan-0.5.dist-info/METADATA
ganquan-0.5.dist-info/WHEEL
ganquan-0.5.dist-info/top_level.txt
ganquan-0.5.dist-info/RECORD
