Metadata-Version: 2.1
Name: ganquan
Version: 0.5
Summary: this is a tesk package
License: Apache-2.0
Classifier: Development Status :: 3 - Alpha
Classifier: Programming Language :: Python :: 3
Classifier: License :: OSI Approved :: Apache Software License
